alak_acl/__init__.py
alak_acl/manager.py
alak_acl/auth/__init__.py
alak_acl/auth/application/__init__.py
alak_acl/auth/application/interface/__init__.py
alak_acl/auth/application/interface/auth_repository.py
alak_acl/auth/application/interface/email_service.py
alak_acl/auth/application/interface/password_hasher.py
alak_acl/auth/application/interface/token_service.py
alak_acl/auth/application/usecases/__init__.py
alak_acl/auth/application/usecases/forgot_password_usecase.py
alak_acl/auth/application/usecases/login_usecase.py
alak_acl/auth/application/usecases/refresh_token_usecase.py
alak_acl/auth/application/usecases/register_usecase.py
alak_acl/auth/application/usecases/reset_password_usecase.py
alak_acl/auth/domain/__init__.py
alak_acl/auth/domain/dtos/__init__.py
alak_acl/auth/domain/dtos/login_dto.py
alak_acl/auth/domain/dtos/login_response_dto.py
alak_acl/auth/domain/dtos/password_reset_dto.py
alak_acl/auth/domain/dtos/register_dto.py
alak_acl/auth/domain/dtos/token_dto.py
alak_acl/auth/domain/entities/__init__.py
alak_acl/auth/domain/entities/auth_user.py
alak_acl/auth/infrastructure/__init__.py
alak_acl/auth/infrastructure/mappers/__init__.py
alak_acl/auth/infrastructure/mappers/auth_user_mapper.py
alak_acl/auth/infrastructure/models/__init__.py
alak_acl/auth/infrastructure/models/mongo_model.py
alak_acl/auth/infrastructure/models/sql_model.py
alak_acl/auth/infrastructure/repositories/__init__.py
alak_acl/auth/infrastructure/repositories/mongodb_repository.py
alak_acl/auth/infrastructure/repositories/mysql_repository.py
alak_acl/auth/infrastructure/repositories/postgresql_repository.py
alak_acl/auth/infrastructure/services/__init__.py
alak_acl/auth/infrastructure/services/argon2_password_hasher.py
alak_acl/auth/infrastructure/services/console_email_service.py
alak_acl/auth/infrastructure/services/jwt_token_service.py
alak_acl/auth/infrastructure/services/smtp_email_service.py
alak_acl/auth/interface/__init__.py
alak_acl/auth/interface/api.py
alak_acl-0.1.38.dist-info/licenses/LICENSE
alak_acl-0.1.38.dist-info/METADATA
alak_acl-0.1.38.dist-info/WHEEL
alak_acl-0.1.38.dist-info/top_level.txt
alak_acl-0.1.38.dist-info/RECORD
