Metadata-Version: 2.4
Name: alak-acl
Version: 0.1.38
Summary: Package professionnel pour gérer l'authentification et les permissions ACL dans FastAPI
Author-email: ALAK Digital <info@alakdigital.com>
License: MIT
Project-URL: Homepage, https://github.com/alakdigital/acl_package
Project-URL: Documentation, https://github.com/alakdigital/acl_package?tab=readme-ov-file
Project-URL: Repository, https://github.com/alakdigital/acl_package.git
Project-URL: Issues, https://github.com/example/fastapi-acl/issues
Keywords: fastapi,acl,authentication,authorization,permissions,jwt,security
Classifier: Development Status :: 4 - Beta
Classifier: Intended Audience :: Developers
Classifier: License :: OSI Approved :: MIT License
Classifier: Operating System :: OS Independent
Classifier: Programming Language :: Python
Classifier: Programming Language :: Python :: 3
Classifier: Programming Language :: Python :: 3 :: Only
Classifier: Programming Language :: Python :: 3.10
Classifier: Programming Language :: Python :: 3.11
Classifier: Programming Language :: Python :: 3.12
Classifier: Framework :: FastAPI
Classifier: Topic :: Internet :: WWW/HTTP
Classifier: Topic :: Internet :: WWW/HTTP :: HTTP Servers
Classifier: Topic :: Security
Classifier: Topic :: Software Development :: Libraries
Classifier: Topic :: Software Development :: Libraries :: Python Modules
Classifier: Typing :: Typed
Requires-Python: >=3.10
License-File: LICENSE
Requires-Dist: fastapi<1.0.0,>=0.111.0
Requires-Dist: pydantic<3.0.0,>=2.0.0
Requires-Dist: pydantic-settings<3.0.0,>=2.0.0
Requires-Dist: python-jose[cryptography]>=3.3.0
Requires-Dist: argon2-cffi>=23.1.0
Requires-Dist: python-multipart>=0.0.6
Requires-Dist: email-validator>=2.0.0
Provides-Extra: postgresql
Requires-Dist: sqlalchemy[asyncio]<3,>=2; extra == "postgresql"
Requires-Dist: asyncpg>=0.31.0; extra == "postgresql"
Provides-Extra: mysql
Requires-Dist: sqlalchemy[asyncio]<3,>=2; extra == "mysql"
Requires-Dist: asyncmy>=0.2.10; extra == "mysql"
Provides-Extra: mongodb
Requires-Dist: motor>=3.3.0; extra == "mongodb"
Provides-Extra: redis
Requires-Dist: redis>=5.0.0; extra == "redis"
Provides-Extra: all
Requires-Dist: sqlalchemy[asyncio]<3,>=2; extra == "all"
Requires-Dist: asyncpg>=0.31.0; extra == "all"
Requires-Dist: asyncmy>=0.2.10; extra == "all"
Requires-Dist: motor>=3.3.0; extra == "all"
Requires-Dist: redis>=5.0.0; extra == "all"
Provides-Extra: dev
Requires-Dist: uvicorn[standard]>=0.24.0; extra == "dev"
Requires-Dist: pytest>=7.4.0; extra == "dev"
Requires-Dist: pytest-asyncio>=0.21.0; extra == "dev"
Requires-Dist: pytest-cov>=4.1.0; extra == "dev"
Requires-Dist: httpx>=0.25.0; extra == "dev"
Requires-Dist: black>=23.0.0; extra == "dev"
Requires-Dist: ruff>=0.1.0; extra == "dev"
Requires-Dist: mypy>=1.5.0; extra == "dev"
Requires-Dist: pre-commit>=3.4.0; extra == "dev"
Provides-Extra: docs
Requires-Dist: mkdocs>=1.5.0; extra == "docs"
Requires-Dist: mkdocs-material>=9.4.0; extra == "docs"
Requires-Dist: mkdocstrings[python]>=0.23.0; extra == "docs"
Dynamic: license-file
